[{"timestamp_utc":"2022-09-09T23:29:20.112Z","context_application_version":"8.7.64.478","context_conn_country":"AR","context_device_manufacturer":"motorola","context_device_model":"moto g(30)","context_os_name":"android","context_os_version":"12","context_receiver_service_timestamp":1662766188464,"context_time":1662766160112,"message_audiocodec":"vorbis","message_bitrate":96000,"message_error_code":11,"message_external_track":false,"message_fatal":false,"message_file_id":"92nlryg1xiiLbZ6jbM+IEhdEes4=","message_playback_id":"guIlqvtDHOAKT8F8YZqxDA==","message_position_ms":215862,"message_track_id":"spotify:track:6phjH1prCWCcKAYiRONHJx"},{"timestamp_utc":"2022-09-10T22:29:12.327Z","context_application_version":"8.7.64.478","context_conn_country":"AR","context_device_manufacturer":"motorola","context_device_model":"moto g(30)","context_os_name":"android","context_os_version":"12","context_receiver_service_timestamp":1662848981991,"context_time":1662848952327,"message_audiocodec":"vorbis","message_bitrate":96000,"message_error_code":11,"message_external_track":false,"message_fatal":false,"message_file_id":"WMPLo1oUq+84e4SX6/FjiI7U0dw=","message_playback_id":"DYYQebOjLpx6SiwO1os/Bg==","message_position_ms":3100,"message_track_id":"spotify:track:7KRQoq9GeWeCm0ZAXg5XMb"},{"timestamp_utc":"2022-09-13T00:04:38.569Z","context_application_version":"8.7.64.478","context_conn_country":"AR","context_device_manufacturer":"motorola","context_device_model":"moto g(30)","context_os_name":"android","context_os_version":"12","context_receiver_service_timestamp":1663027504241,"context_time":1663027478569,"message_audiocodec":"vorbis","message_bitrate":96000,"message_error_code":11,"message_external_track":false,"message_fatal":false,"message_file_id":"q2BXV27ilGeoYqjWB2MDPAjwhYA=","message_playback_id":"ZeXr1+/PQ0dHnowmxyo5ag==","message_position_ms":523,"message_track_id":"spotify:track:3cp8xX1N5jewfKU2oY2Y08"},{"timestamp_utc":"2022-09-11T15:57:36.191Z","context_application_version":"8.7.64.478","context_conn_country":"AR","context_device_manufacturer":"motorola","context_device_model":"moto g(30)","context_os_name":"android","context_os_version":"12","context_receiver_service_timestamp":1662911898936,"context_time":1662911856191,"message_audiocodec":"vorbis","message_bitrate":96000,"message_error_code":11,"message_external_track":false,"message_fatal":false,"message_file_id":"L67lWj9CDXwt2aJhYdGiAnkOvmU=","message_playback_id":"uPSCIhyKJy/4PQ6ncDb+4A==","message_position_ms":184323,"message_track_id":"spotify:track:5g7uidL6cVNS7GxcCAXa19"},{"timestamp_utc":"2022-09-13T11:23:58.673Z","context_application_version":"8.7.64.478","context_conn_country":"AR","context_device_manufacturer":"motorola","context_device_model":"moto g(30)","context_os_name":"android","context_os_version":"12","context_receiver_service_timestamp":1663068262312,"context_time":1663068238673,"message_audiocodec":"vorbis","message_bitrate":96000,"message_error_code":11,"message_external_track":false,"message_fatal":false,"message_file_id":"wAqTkUppkTs1S7Ype9cMCp7lJdU=","message_playback_id":"cCYU7IjEY7Khyu7pdmoA2w==","message_position_ms":175614,"message_track_id":"spotify:track:4QHKR48C18rwlpSYW6rH7p"},{"timestamp_utc":"2022-09-08T04:18:05.787Z","context_application_version":"8.7.62.398","context_conn_country":"AR","context_device_manufacturer":"motorola","context_device_model":"moto g(30)","context_os_name":"android","context_os_version":"12","context_receiver_service_timestamp":1662610715168,"context_time":1662610685787,"message_audiocodec":"vorbis","message_bitrate":96000,"message_error_code":11,"message_external_track":false,"message_fatal":false,"message_file_id":"4+od7p3/Gsj+6pMw61aF7hRnOdQ=","message_playback_id":"IrubkrPmA/dIx6VPWkoK1A==","message_position_ms":113302,"message_track_id":"spotify:track:4HMkwVwMObudZpowtfQ2UE"}]